py_loop/__init__.py
py_loop/looper.py
py_loop/main.py
py_loop-0.5.1.dist-info/LICENSE
py_loop-0.5.1.dist-info/METADATA
py_loop-0.5.1.dist-info/WHEEL
py_loop-0.5.1.dist-info/entry_points.txt
py_loop-0.5.1.dist-info/RECORD
