Metadata-Version: 2.1
Name: py-loop
Version: 0.5.1
Summary: Run commands until it fails
Author: jerem
Author-email: jeremy.tellaa@tanker.io
Requires-Python: >=3.8.1,<4.0
Classifier: Programming Language :: Python :: 3
Classifier: Programming Language :: Python :: 3.9
Classifier: Programming Language :: Python :: 3.10
Classifier: Programming Language :: Python :: 3.11
Classifier: Programming Language :: Python :: 3.12
Requires-Dist: cli-ui (>=0.17.2,<0.18.0)
